ckanext/__init__.py
ckanext/drupal_idp/__init__.py
ckanext/drupal_idp/cli.py
ckanext/drupal_idp/config.py
ckanext/drupal_idp/drupal.py
ckanext/drupal_idp/helpers.py
ckanext/drupal_idp/plugin.py
ckanext/drupal_idp/signals.py
ckanext/drupal_idp/utils.py
ckanext/drupal_idp/views.py
ckanext/drupal_idp/logic/__init__.py
ckanext/drupal_idp/logic/action.py
ckanext/drupal_idp/logic/auth.py
ckanext/drupal_idp/tests/__init__.py
ckanext/drupal_idp/tests/conftest.py
ckanext/drupal_idp/tests/test_drupal.py
ckanext/drupal_idp/tests/test_plugin.py
ckanext/drupal_idp/tests/test_utils.py
ckanext/drupal_idp/tests/logic/__init__.py
ckanext/drupal_idp/tests/logic/test_action.py
ckanext_drupal_idp-0.5.0.dist-info/METADATA
ckanext_drupal_idp-0.5.0.dist-info/WHEEL
ckanext_drupal_idp-0.5.0.dist-info/entry_points.txt
ckanext_drupal_idp-0.5.0.dist-info/top_level.txt
ckanext_drupal_idp-0.5.0.dist-info/RECORD
