Metadata-Version: 2.1
Name: ckanext-drupal-idp
Version: 0.5.0
Summary: Login to CKAN using Drupal session cookie
Author-email: DataShades <datashades@linkdigital.com.au>, Sergey Motornyuk <sergey.motornyuk@linkdigital.com.au>
Maintainer-email: DataShades <datashades@linkdigital.com.au>
License: AGPL
Project-URL: Homepage, https://github.com/DataShades/ckanext-drupal-idp
Keywords: CKAN
Requires-Dist: typing-extensions >=4.1.0
Requires-Dist: blinker
Requires-Dist: ckanext-toolbelt
Provides-Extra: mysql
Requires-Dist: mysqlclient ; extra == 'mysql'
